xm_ai/__init__.py
xm_ai/aws_utils.py
xm_ai/database_utils.py
xm_ai/email_utils.py
xm_ai/excel_utils.py
xm_ai/query_utils.py
xm_ai/syntax_utils.py
xm_ai/time_utils.py
xm_ai-0.11.dist-info/METADATA
xm_ai-0.11.dist-info/WHEEL
xm_ai-0.11.dist-info/top_level.txt
xm_ai-0.11.dist-info/RECORD
