Metadata-Version: 2.1
Name: xm-ai
Version: 0.11
Summary: A package of utilities for xMentium's AI Team
Home-page: UNKNOWN
Author: Noah Caldwell
Author-email: noah@xmentium.com
License: UNKNOWN
Keywords: utilities,ai
Platform: UNKNOWN
Classifier: Intended Audience :: Developers
Classifier: Programming Language :: Python :: 3.10
Requires-Dist: boto3 (==1.26.67)
Requires-Dist: botocore (==1.29.67)
Requires-Dist: pymongo (==4.3.3)
Requires-Dist: utils (==1.0.1)
